flask_add_ons/__init__.py
flask_add_ons/logging.py
flask_add_ons-0.1.dist-info/METADATA
flask_add_ons-0.1.dist-info/WHEEL
flask_add_ons-0.1.dist-info/top_level.txt
flask_add_ons-0.1.dist-info/RECORD
