Metadata-Version: 2.1
Name: flask-add-ons
Version: 0.1
Summary: Flask add ons
Home-page: https://github.com/dameyerdave/flask-add-ons
Author: David Meyer
Author-email: dameyerdave@gmail.com
License: UNKNOWN
Platform: UNKNOWN
Classifier: Programming Language :: Python :: 3
Classifier: License :: OSI Approved :: MIT License
Classifier: Operating System :: OS Independent
Requires-Python: >=3.5
Requires-Dist: blessings
